Workbook

Sheet Resumen
A1: RESUMEN DE FACTURAS
A2: Pastorino Costa del Sol SL (CIF: B13995519)
A3: Período: Julio 2025 - Marzo 2026
A5: Categoría | B5: Nº Facturas | C5: Total (EUR)
A6: INGRESOS (Facturas emitidas) | B6: 4 | C6: =Ingresos!J6 -> 144535.63
A7: GASTOS - Transporte (Primafrio) | B7: 4 | C7: =SUM(Gastos!K3:K6) -> 3872
A8: GASTOS - Aduanas/Logística (Primafrio) | B8: 6 | C8: =SUM(Gastos!K7:K12) -> 27532.9
A9: GASTOS - Aduanas (Transitainer) | B9: 1 | C9: =Gastos!K13 -> 6908.82
A10: GASTOS - Software (Odoo) | B10: 3 | C10: =SUM(Gastos!K14:K16) -> 47.51
A11: GASTOS - Naviera Maersk (Importación) | B11: 3 | C11: =SUM(Gastos!K17:K19) -> 501
A12: GASTOS - Maersk (Demoras terminal) | B12: 5 | C12: =SUM(Gastos!K20:K24) -> 4590
A13: GASTOS - Maersk (Detención contenedor) | B13: 6 | C13: =SUM(Gastos!K25:K30) -> 5580
A14: GASTOS - Maersk (CSI-Fresh Rotterdam) | B14: 2 | C14: =SUM(Gastos!K31:K32) -> 648
A15: GASTOS - Compras (El Corte Inglés) | B15: 2 | C15: =SUM(Gastos!K33:K34) -> 1227.11
A16: GASTOS - Publicidad (Copyrap) | B16: 1 | C16: =Gastos!K35 -> 42.42
A17: GASTOS - Seguro (Coface) | B17: 1 | C17: =Gastos!K2 -> 536.75
A18: GASTOS - Mercancía (Cauquen, USD) | B18: 1 | C18: 8.800,00 USD
A20: TOTAL INGRESOS | C20: =Ingresos!J6 -> 144535.63
A21: TOTAL GASTOS (EUR, sin Cauquen) | C21: =Gastos!K37 -> 60286.51
A23: NOTAS:
A24: 1. La factura 7532598836 (Maersk) no se pudo leer. Revisar manualmente.
A25: 2. Las liquidaciones de Malaga Natural corresponden a las facturas INV emitidas (mismas operaciones).
A26: 3. La factura de Cauquen Argentina está en USD (8.800,00 USD).
A27: 4. Facturas 7536263946 y 7537075071 de Maersk están a nombre de CSI-Fresh BV (Holanda).
A28: 5. Los CMR (cartas de porte) no son facturas, son documentos de transporte.

Sheet Ingresos
A1: Nº | B1: Archivo | C1: Nº Factura | D1: Fecha | E1: Cliente | F1: Concepto | G1: Base Imponible | H1: IVA (%) | I1: Cuota IVA | J1: Total
A2: 1 | B2: INV_2025_00001.pdf | C2: INV/2025/00001 | D2: 09/08/2025 | E2: Malaga Natural 2012 SL | F2: Venta limones (Container SUDU8020260) | G2: 34117.2 | H2: 4% | I2: 1364.69 | J2: 35481.89
A3: 2 | B3: INV_2025_00002.pdf | C3: INV/2025/00002 | D3: 25/08/2025 | E3: Malaga Natural 2012 SL | F3: Venta limones (Containers SUDU8020260/MNBU0233449) | G3: 34933.68 | H3: 4% | I3: 1397.34 | J3: 36331.02
A4: 3 | B4: INV_2025_00003.pdf | C4: INV/2025/00003 | D4: 25/08/2025 | E4: Malaga Natural 2012 SL | F4: Venta limones (Containers MNBU0233449/SUDU6177121) | G4: 34992 | H4: 4% | I4: 1399.69 | J4: 36391.69
A5: 4 | B5: INV_2025_00004.pdf | C5: INV/2025/00004 | D5: 25/08/2025 | E5: Malaga Natural 2012 SL | F5: Venta limones (Container SUDU6177121) | G5: 34933.68 | H5: 4% | I5: 1397.35 | J5: 36331.03
F6: TOTAL INGRESOS | G6: =SUM(G2:G5) -> 138976.56 | I6: =SUM(I2:I5) -> 5559.07 | J6: =SUM(J2:J5) -> 144535.63

Sheet Gastos
A1: Nº | B1: Archivo | C1: Nº Factura | D1: Fecha | E1: Proveedor | F1: Categoría | G1: Concepto | H1: Base Imponible | I1: IVA (%) | J1: Cuota IVA | K1: Total | L1: Moneda
A2: 1 | B2: 01PRMR523886.pdf | C2: 523886 | D2: 02/03/2026 | E2: Coface (Compagnie Française d'Assurance) | F2: Seguro | G2: Prima seguro crédito exportación | H2: 500 | I2: IPS 8% + RAL 0.15% | J2: 36.75 | K2: 536.75 | L2: EUR
A3: 2 | B3: 1090161585.pdf | C3: 1090161585 | D3: 30/07/2025 | E3: Primafrio SL | F3: Transporte | G3: Transporte contenedor Portugal-Málaga (limones) | H3: 800 | I3: 21% | J3: 168 | K3: 968 | L3: EUR
A4: 3 | B4: 1090165048.pdf | C4: 1090165048 | D4: 06/08/2025 | E4: Primafrio SL | F4: Transporte | G4: Transporte contenedor Portugal-Málaga (limones) | H4: 800 | I4: 21% | J4: 168 | K4: 968 | L4: EUR
A5: 4 | B5: 1090167087.pdf | C5: 1090167087 | D5: 08/08/2025 | E5: Primafrio SL | F5: Transporte | G5: Transporte contenedor Portugal-Málaga | H5: 800 | I5: 21% | J5: 168 | K5: 968 | L5: EUR
A6: 5 | B6: 1090168047.pdf | C6: 1090168047 | D6: 12/08/2025 | E6: Primafrio SL | F6: Transporte | G6: Transporte contenedor Portugal-Málaga (limones) | H6: 800 | I6: 21% | J6: 168 | K6: 968 | L6: EUR
A7: 6 | B7: 2390101398.pdf | C7: 2390101398 | D7: 27/08/2025 | E7: Primafrio SL | F7: Aduanas/Logística | G7: Despacho aduanas cont. SUDU8020260 (aranceles, IVA aduana, fito, inspección) | H7: 7294.33 | I7: Mixto | J7: 483.53 | K7: 7777.86 | L7: EUR
A8: 7 | B8: 2390101399.pdf | C8: 2390101399 | D8: 27/08/2025 | E8: Primafrio SL | F8: Aduanas/Logística | G8: Despacho aduanas cont. MNBU0233449 (aranceles, fito, logística) | H8: 7608.29 | I8: Mixto | J8: 380.36 | K8: 7988.65 | L8: EUR
A9: 8 | B9: 2390101400.pdf | C9: 2390101400 | D9: 27/08/2025 | E9: Primafrio SL | F9: Aduanas/Logística | G9: Despacho aduanas cont. SUDU6177121 (aranceles, IVA aduana, fito) | H9: 7372.26 | I9: Mixto | J9: 371.44 | K9: 7743.7 | L9: EUR
A10: 9 | B10: 2390101460.pdf | C10: 2390101460 | D10: 17/09/2025 | E10: Primafrio SL | F10: Aduanas/Logística | G10: Flete marítimo + aduanas cont. MNBU4144463 | H10: 11040.63 | I10: Mixto | J10: 250.38 | K10: 11291.01 | L10: EUR
A11: 10 | B11: 2390102446.pdf | C11: 2390102446 | D11: 30/12/2025 | E11: Primafrio SL | F11: Aduanas/Logística | G11: Costes naviera + logística cont. MNBU4144463 | H11: 1880.3 | I11: Mixto | J11: 250.38 | K11: 2130.68 | L11: EUR
A12: 11 | B12: 2390400070.pdf | C12: 2390400070 | D12: 30/12/2025 | E12: Primafrio SL | F12: Abono | G12: ABONO ref. factura 2390101702 cont. MNBU4144463 | H12: -9148.62 | I12: Mixto | J12: -250.38 | K12: -9399 | L12: EUR
A13: 12 | B13: Fatura TT FT25S_000116.pdf | C13: TT FT25S/000116 | D13: 14/08/2025 | E13: Transitainer Portugal Ltda | F13: Aduanas/Logística | G13: Despacho aduanas cont. MNBU0233449 (aranceles, IVA import., fito) | H13: 6908.82 | I13: 0% (IVA M0) | J13: 0 | K13: 6908.82 | L13: EUR
... A16: 15 | B16: INV_2025_10_00669.pdf | C16: INV/2025/10/00669 | D16: 09/10/2025 | E16: Odoo ERP SP SL (España) | F16: Software | G16: Suscripción Odoo Enterprise (octubre) | H16: 14.8 | I16: 21% | J16: 3.11 | K16: 17.91 | L16: EUR
A17: 16 | B17: 7532598836.pdf | C17: 7532598836 | D17: Jul 2025 | E17: Maersk | F17: Naviera/Importación | G17: Factura importación cont. SUDU8020260 (REVISAR IMPORTE) | I17: 0% (exento) | L17: EUR
A18: 17 | B18: 7532745537.pdf | C18: 7532745537 | D18: 06/07/2025 | E18: Maersk | F18: Naviera/Importación | G18: Terminal + documentación + seguro cont. MNBU0233449 | H18: 378 | I18: 0% (exento) | J18: 0 | K18: 378 | L18: EUR
A19: 18 | B19: 7533442509.pdf | C19: 7533442509 | D19: 18/07/2025 | E19: Maersk | F19: Naviera/Importación | G19: Generador transporte terrestre cont. SUDU8020260 | H19: 123 | I19: 0% (exento) | J19: 0 | K19: 123 | L19: EUR
A20: 19 | B20: 7533441178.pdf | C20: 7533441178 | D20: 18/07/2025 | E20: Maersk | F20: Demoras terminal | G20: Recargo demora cont. SUDU8020260 (19 días) | H20: 2510 | I20: 0% (exento) | J20: 0 | K20: 2510 | L20: EUR
A21: 20 | B21: 7533463809.pdf | C21: 7533463809 | D21: 18/07/2025 | E21: Maersk | F21: Demoras terminal | G21: Recargo demora cont. MNBU0233449 (11 días) | H21: 1390 | I21: 0% (exento) | J21: 0 | K21: 1390 | L21: EUR
A22: 21 | B22: 7533589808.pdf | C22: 7533589808 | D22: Jul 2025 | E22: Maersk | F22: Demoras terminal | G22: Recargo demora cont. SUDU6177121 (4 días) | H22: 440 | I22: 0% (exento) | J22: 0 | K22: 440 | L22: EUR
A23: 22 | B23: 7533642938.pdf | C23: 7533642938 | D23: 22/07/2025 | E23: Maersk | F23: Demoras terminal | G23: Recargo demora cont. SUDU6177121 (1 día) | H23: 110 | I23: 0% (exento) | J23: 0 | K23: 110 | L23: EUR
A24: 23 | B24: 7533658621.pdf | C24: 7533658621 | D24: 22/07/2025 | E24: Maersk | F24: Demoras terminal | G24: Recargo demora cont. SUDU6177121 (1 día) | H24: 140 | I24: 0% (exento) | J24: 0 | K24: 140 | L24: EUR
A25: 24 | B25: 7533441271.pdf | C25: 7533441271 | D25: 18/07/2025 | E25: Maersk | F25: Detención contenedor | G25: Detención cont. SUDU8020260 (17 días) | H25: 3060 | I25: 0% (exento) | J25: 0 | K25: 3060 | L25: EUR
A26: 25 | B26: 7533463896.pdf | C26: 7533463896 | D26: 18/07/2025 | E26: Maersk | F26: Detención contenedor | G26: Detención cont. MNBU0233449 (9 días) | H26: 1620 | I26: 0% (exento) | J26: 0 | K26: 1620 | L26: EUR
A27: 26 | B27: 7533590105.pdf | C27: 7533590105 | D27: Jul 2025 | E27: Maersk | F27: Detención contenedor | G27: Detención cont. SUDU6177121 (2 días) | H27: 360 | I27: 0% (exento) | J27: 0 | K27: 360 | L27: EUR
A28: 27 | B28: 7533642998.pdf | C28: 7533642998 | D28: 22/07/2025 | E28: Maersk | F28: Detención contenedor | G28: Detención cont. SUDU6177121 (1 día) | H28: 180 | I28: 0% (exento) | J28: 0 | K28: 180 | L28: EUR
A29: 28 | B29: 7533658622.pdf | C29: 7533658622 | D29: 22/07/2025 | E29: Maersk | F29: Detención contenedor | G29: Detención cont. SUDU6177121 (1 día) | H29: 180 | I29: 0% (exento) | J29: 0 | K29: 180 | L29: EUR
... A35: 34 | B35: Factura 23355T.pdf | C35: T-AUR-25/023355 | D35: 30/09/2025 | E35: Soc. Andaluza de Publicidad (Copyrap) | F35: Publicidad | G35: 100 tarjetas de visita impresas | H35: 35.06 | I35: 21% | J35: 7.36 | K35: 42.42 | L35: EUR
A36: 35 | B36: Invoice E 00005-00004696.pdf | C36: E 00005-00004696 | D36: 28/07/2025 | E36: Cauquen Argentina SA | F36: Mercancía (importación) | G36: Limones FOB Argentina (1440 cajas, cont. MNBU4144463) | I36: N/A | K36: 8800 | L36: USD
G37: TOTAL GASTOS (EUR) | H37: =SUM(H2:H36) -> 49068.61 | J37: =SUM(J2:J36) -> 2417.9 | K37: =SUM(K2:K36) -> 60286.51

Sheet Liquidaciones
A1: Nº | B1: Archivo | C1: Fecha | D1: Emisor | E1: Concepto | F1: Kg Netos | G1: Subtotal | H1: Dto. 10% | I1: Base Imponible | J1: IVA (4%) | K1: Total
A2: 1 | B2: Factura proveedores - Borrador_20250807_090407.pdf | C2: 10/07/2025 | D2: Malaga Natural 2012 SL | E2: Liquidación venta limones (1er envío, cont. SUDU8020260) | F2: 19440 | G2: 37908 | H2: 3790.8 | I2: 34117.2 | J2: 1364.69 | K2: 35481.89
A3: 2 | B3: Factura proveedores segundo envio - Borrador_20250816_075941.pdf | C3: 23/07/2025 | D3: Malaga Natural 2012 SL | E3: Liquidación venta limones (2do envío) | F3: 19440 | G3: 38815.2 | H3: 3881.52 | I3: 34933.68 | J3: 1397.35 | K3: 36331.03
A4: 3 | B4: Factura proveedores tercer envio - Borrador_20250816_080043.pdf | C4: 24/07/2025 | D4: Malaga Natural 2012 SL | E4: Liquidación venta limones (3er envío) | F4: 19440 | G4: 38880 | H4: 3888 | I4: 34992 | J4: 1399.68 | K4: 36391.68
A5: 4 | B5: Factura proveedores - cuarto envio Borrador_20250816_080156.pdf | C5: 24/07/2025 | D5: Malaga Natural 2012 SL | E5: Liquidación venta limones (4to envío) | F5: 19440 | G5: 38815.2 | H5: 3881.52 | I5: 34933.68 | J5: 1397.35 | K5: 36331.03
E6: TOTAL LIQUIDACIONES | F6: =SUM(F2:F5) -> 77760 | G6: =SUM(G2:G5) -> 154418.4 | H6: =SUM(H2:H5) -> 15441.84 | I6: =SUM(I2:I5) -> 138976.56 | J6: =SUM(J2:J5) -> 5559.07 | K6: =SUM(K2:K5) -> 144535.63

Sheet Otros Documentos
A1: Nº | B1: Archivo | C1: Fecha | D1: Tipo | E1: Descripción
A2: 1 | B2: 3575_250905150252_009.pdf | C2: 05/09/2025 | D2: CMR / Carta de porte | E2: Documento de transporte terrestre CSI-Fresh BV (Barendrecht, NL)
A3: 2 | B3: 3592_250908143329_001.pdf | C3: 08/09/2025 | D3: CMR / Carta de porte | E3: Documento de transporte terrestre CSI-Fresh BV (Barendrecht, NL)
